auditd_ripper/__init__.py
auditd_ripper/main.py
auditd_ripper-0.1.3.dist-info/METADATA
auditd_ripper-0.1.3.dist-info/WHEEL
auditd_ripper-0.1.3.dist-info/entry_points.txt
auditd_ripper-0.1.3.dist-info/RECORD
